README.rst
docgrep.py
setup.py
docgrep.egg-info/PKG-INFO
docgrep.egg-info/SOURCES.txt
docgrep.egg-info/dependency_links.txt
docgrep.egg-info/entry_points.txt
docgrep.egg-info/top_level.txt