Metadata-Version: 1.1
Name: docgrep
Version: 0.1
Summary: Like grep, but searches for matches in docstrings.
Home-page: https://github.com/myint/docgrep
Author: Steven Myint
Author-email: UNKNOWN
License: Expat License
Keywords: grep,search,docstrings
Platform: UNKNOWN
Classifier: Intended Audience :: Developers
Classifier: Environment :: Console
Classifier: Programming Language :: Python :: 2.7
Classifier: Programming Language :: Python :: 3
Classifier: Programming Language :: Python :: 3.4
Classifier: License :: OSI Approved :: MIT License
